src/demux.v
module demux_1_64 (
    input  wire        data_in,  // 1-bit input data signal
    input  wire [5:0]  sel,      // 6-bit select line (2^6 = 64 outputs)
    output reg  [63:0] data_out  // 64-bit output bus
);

    // Behavioral description for combinational logic
    always @(*) begin
        // Default assignment: All outputs are driven LOW
        data_out = 64'b0;
        
        // Route the input signal to the specifically selected output bit
        data_out[sel] = data_in;
    end

endmodule

src/demuxtb.v
`timescale 1ns / 1ps

module demux_1_64_tb;

    // Inputs (driven as registers in testbench)
    reg data_in;
    reg [5:0] sel;

    // Outputs (monitored as wires)
    wire [63:0] data_out;

    // Instantiate the Unit Under Test (UUT)
    // Ensure the module name here matches the module name inside demux.v
    demux_1_64 uut (
        .data_in(data_in),
        .sel(sel),
        .data_out(data_out)
    );

    // Loop variable for simulation stimulus
    integer i;

    // --- Waveform Generation Block ---
    initial begin
        $dumpfile("demux_waveform.vcd"); // Creates the VCD file in the execution folder
        $dumpvars(0, demux_1_64_tb);     // Dumps all signals within this testbench module
    end

    // --- Main Simulation Stimulus ---
    initial begin
        // Initialize Inputs
        data_in = 1'b0;
        sel = 6'b000000;

        // Global reset emulation window
        #100;
        
        // --- Test Case 1: Drive Data HIGH across all 64 channels ---
        $display("Starting Test Case 1: Routing HIGH data signal...");
        data_in = 1'b1;
        
        for (i = 0; i < 64; i = i + 1) begin
            sel = i;
            #10; // Propagation delay padding
            
            // Self-checking assertion
            if (data_out[i] !== 1'b1) begin
                $display("ALERT: Verification mismatch detected at output channel %d", i);
            end
        end

        // --- Test Case 2: Drive Data LOW and verify channel updates ---
        $display("Starting Test Case 2: Routing LOW data signal...");
        data_in = 1'b0;
        sel = 6'd32; // Fully sized 6-bit literal index
        #10;
        
        if (data_out[32] !== 1'b0) begin
            $display("ALERT: Data failed to pull down on channel 32");
        end

        // End Simulation cleanly
        $display("Execution Matrix Completed: All checks processed.");
        $finish;
    end
      
endmodule

src/demux_waveform.vcd
$date
	Wed Jun 24 22:12:31 2026
$end
$version
	Icarus Verilog
$end
$timescale
	1ps
$end
$scope module demux_1_64_tb $end
$var wire 64 ! data_out [63:0] $end
$var reg 1 " data_in $end
$var reg 6 # sel [5:0] $end
$var integer 32 $ i [31:0] $end
$scope module uut $end
$var wire 1 " data_in $end
$var wire 6 % sel [5:0] $end
$var reg 64 & data_out [63:0] $end
$upscope $end
$upscope $end
$enddefinitions $end
$comment Show the parameter values. $end
$dumpall
$end
#0
$dumpvars
b0 &
b0 %
bx $
b0 #
0"
b0 !
$end
#100000
b1 !
b1 &
b0 $
1"
#110000
b10 !
b10 &
b1 #
b1 %
b1 $
#120000
b100 !
b100 &
b10 #
b10 %
b10 $
#130000
b1000 !
b1000 &
b11 #
b11 %
b11 $
#140000
b10000 !
b10000 &
b100 #
b100 %
b100 $
#150000
b100000 !
b100000 &
b101 #
b101 %
b101 $
#160000
b1000000 !
b1000000 &
b110 #
b110 %
b110 $
#170000
b10000000 !
b10000000 &
b111 #
b111 %
b111 $
#180000
b100000000 !
b100000000 &
b1000 #
b1000 %
b1000 $
#190000
b1000000000 !
b1000000000 &
b1001 #
b1001 %
b1001 $
#200000
b10000000000 !
b10000000000 &
b1010 #
b1010 %
b1010 $
#210000
b100000000000 !
b100000000000 &
b1011 #
b1011 %
b1011 $
#220000
b1000000000000 !
b1000000000000 &
b1100 #
b1100 %
b1100 $
#230000
b10000000000000 !
b10000000000000 &
b1101 #
b1101 %
b1101 $
#240000
b100000000000000 !
b100000000000000 &
b1110 #
b1110 %
b1110 $
#250000
b1000000000000000 !
b1000000000000000 &
b1111 #
b1111 %
b1111 $
#260000
b10000000000000000 !
b10000000000000000 &
b10000 #
b10000 %
b10000 $
#270000
b100000000000000000 !
b100000000000000000 &
b10001 #
b10001 %
b10001 $
#280000
b1000000000000000000 !
b1000000000000000000 &
b10010 #
b10010 %
b10010 $
#290000
b10000000000000000000 !
b10000000000000000000 &
b10011 #
b10011 %
b10011 $
#300000
b100000000000000000000 !
b100000000000000000000 &
b10100 #
b10100 %
b10100 $
#310000
b1000000000000000000000 !
b1000000000000000000000 &
b10101 #
b10101 %
b10101 $
#320000
b10000000000000000000000 !
b10000000000000000000000 &
b10110 #
b10110 %
b10110 $
#330000
b100000000000000000000000 !
b100000000000000000000000 &
b10111 #
b10111 %
b10111 $
#340000
b1000000000000000000000000 !
b1000000000000000000000000 &
b11000 #
b11000 %
b11000 $
#350000
b10000000000000000000000000 !
b10000000000000000000000000 &
b11001 #
b11001 %
b11001 $
#360000
b100000000000000000000000000 !
b100000000000000000000000000 &
b11010 #
b11010 %
b11010 $
#370000
b1000000000000000000000000000 !
b1000000000000000000000000000 &
b11011 #
b11011 %
b11011 $
#380000
b10000000000000000000000000000 !
b10000000000000000000000000000 &
b11100 #
b11100 %
b11100 $
#390000
b100000000000000000000000000000 !
b100000000000000000000000000000 &
b11101 #
b11101 %
b11101 $
#400000
b1000000000000000000000000000000 !
b1000000000000000000000000000000 &
b11110 #
b11110 %
b11110 $
#410000
b10000000000000000000000000000000 !
b10000000000000000000000000000000 &
b11111 #
b11111 %
b11111 $
#420000
b100000000000000000000000000000000 !
b100000000000000000000000000000000 &
b100000 #
b100000 %
b100000 $
#430000
b1000000000000000000000000000000000 !
b1000000000000000000000000000000000 &
b100001 #
b100001 %
b100001 $
#440000
b10000000000000000000000000000000000 !
b10000000000000000000000000000000000 &
b100010 #
b100010 %
b100010 $
#450000
b100000000000000000000000000000000000 !
b100000000000000000000000000000000000 &
b100011 #
b100011 %
b100011 $
#460000
b1000000000000000000000000000000000000 !
b1000000000000000000000000000000000000 &
b100100 #
b100100 %
b100100 $
#470000
b10000000000000000000000000000000000000 !
b10000000000000000000000000000000000000 &
b100101 #
b100101 %
b100101 $
#480000
b100000000000000000000000000000000000000 !
b100000000000000000000000000000000000000 &
b100110 #
b100110 %
b100110 $
#490000
b1000000000000000000000000000000000000000 !
b1000000000000000000000000000000000000000 &
b100111 #
b100111 %
b100111 $
#500000
b10000000000000000000000000000000000000000 !
b10000000000000000000000000000000000000000 &
b101000 #
b101000 %
b101000 $
#510000
b100000000000000000000000000000000000000000 !
b100000000000000000000000000000000000000000 &
b101001 #
b101001 %
b101001 $
#520000
b1000000000000000000000000000000000000000000 !
b1000000000000000000000000000000000000000000 &
b101010 #
b101010 %
b101010 $
#530000
b10000000000000000000000000000000000000000000 !
b10000000000000000000000000000000000000000000 &
b101011 #
b101011 %
b101011 $
#540000
b100000000000000000000000000000000000000000000 !
b100000000000000000000000000000000000000000000 &
b101100 #
b101100 %
b101100 $
#550000
b1000000000000000000000000000000000000000000000 !
b1000000000000000000000000000000000000000000000 &
b101101 #
b101101 %
b101101 $
#560000
b10000000000000000000000000000000000000000000000 !
b10000000000000000000000000000000000000000000000 &
b101110 #
b101110 %
b101110 $
#570000
b100000000000000000000000000000000000000000000000 !
b100000000000000000000000000000000000000000000000 &
b101111 #
b101111 %
b101111 $
#580000
b1000000000000000000000000000000000000000000000000 !
b1000000000000000000000000000000000000000000000000 &
b110000 #
b110000 %
b110000 $
#590000
b10000000000000000000000000000000000000000000000000 !
b10000000000000000000000000000000000000000000000000 &
b110001 #
b110001 %
b110001 $
#600000
b100000000000000000000000000000000000000000000000000 !
b100000000000000000000000000000000000000000000000000 &
b110010 #
b110010 %
b110010 $
#610000
b1000000000000000000000000000000000000000000000000000 !
b1000000000000000000000000000000000000000000000000000 &
b110011 #
b110011 %
b110011 $
#620000
b10000000000000000000000000000000000000000000000000000 !
b10000000000000000000000000000000000000000000000000000 &
b110100 #
b110100 %
b110100 $
#630000
b100000000000000000000000000000000000000000000000000000 !
b100000000000000000000000000000000000000000000000000000 &
b110101 #
b110101 %
b110101 $
#640000
b1000000000000000000000000000000000000000000000000000000 !
b1000000000000000000000000000000000000000000000000000000 &
b110110 #
b110110 %
b110110 $
#650000
b10000000000000000000000000000000000000000000000000000000 !
b10000000000000000000000000000000000000000000000000000000 &
b110111 #
b110111 %
b110111 $
#660000
b100000000000000000000000000000000000000000000000000000000 !
b100000000000000000000000000000000000000000000000000000000 &
b111000 #
b111000 %
b111000 $
#670000
b1000000000000000000000000000000000000000000000000000000000 !
b1000000000000000000000000000000000000000000000000000000000 &
b111001 #
b111001 %
b111001 $
#680000
b10000000000000000000000000000000000000000000000000000000000 !
b10000000000000000000000000000000000000000000000000000000000 &
b111010 #
b111010 %
b111010 $
#690000
b100000000000000000000000000000000000000000000000000000000000 !
b100000000000000000000000000000000000000000000000000000000000 &
b111011 #
b111011 %
b111011 $
#700000
b1000000000000000000000000000000000000000000000000000000000000 !
b1000000000000000000000000000000000000000000000000000000000000 &
b111100 #
b111100 %
b111100 $
#710000
b10000000000000000000000000000000000000000000000000000000000000 !
b10000000000000000000000000000000000000000000000000000000000000 &
b111101 #
b111101 %
b111101 $
#720000
b100000000000000000000000000000000000000000000000000000000000000 !
b100000000000000000000000000000000000000000000000000000000000000 &
b111110 #
b111110 %
b111110 $
#730000
b1000000000000000000000000000000000000000000000000000000000000000 !
b1000000000000000000000000000000000000000000000000000000000000000 &
b111111 #
b111111 %
b111111 $
#740000
b0 !
b0 &
b100000 #
b100000 %
0"
b1000000 $
